CHANGES.rst
CONTRIBUTORS.rst
LICENSE
MANIFEST.in
README.rst
setup.py
xmpp/__init__.py
xmpp/auth.py
xmpp/browser.py
xmpp/cli.py
xmpp/client.py
xmpp/commands.py
xmpp/debug.py
xmpp/dispatcher.py
xmpp/features.py
xmpp/filetransfer.py
xmpp/protocol.py
xmpp/roster.py
xmpp/session.py
xmpp/simplexml.py
xmpp/transports.py
xmpp/xep0106.py
xmpppy.egg-info/PKG-INFO
xmpppy.egg-info/SOURCES.txt
xmpppy.egg-info/dependency_links.txt
xmpppy.egg-info/entry_points.txt
xmpppy.egg-info/top_level.txt