Metadata-Version: 1.1
Name: xmpppy
Version: 0.6.4
Summary: XMPP implementation in Python
Home-page: http://xmpppy.sourceforge.net/
Author: Alexey Nezhdanov
Author-email: snakeru@users.sourceforge.net
License: GPL
Download-URL: https://pypi.org/project/xmpppy/
Keywords: jabber,xmpp,RFC3920,RFC3921
Platform: All
Classifier: Programming Language :: Python
Classifier: Programming Language :: Python :: 2
Classifier: Programming Language :: Python :: 3
Classifier: License :: OSI Approved :: GNU General Public License (GPL)
Classifier: Development Status :: 4 - Beta
Classifier: Operating System :: OS Independent
Classifier: Natural Language :: English
Classifier: Intended Audience :: Developers
Classifier: Intended Audience :: Education
Classifier: Intended Audience :: Information Technology
Classifier: Intended Audience :: System Administrators
Classifier: Intended Audience :: Telecommunications Industry
Classifier: Topic :: Communications
Classifier: Topic :: Communications :: Chat
Classifier: Topic :: Database
Classifier: Topic :: Internet
Classifier: Topic :: Software Development :: Libraries
Classifier: Topic :: System :: Networking
Classifier: Topic :: Text Processing
Classifier: Topic :: Utilities
